trajectopy/LICENSE
trajectopy/__init__.py
trajectopy/__main__.py
trajectopy/__version__.py
trajectopy/exceptions.py
trajectopy/py.typed
trajectopy/cli/__init__.py
trajectopy/cli/main.py
trajectopy/core/__init__.py
trajectopy/core/positions.py
trajectopy/core/rotations.py
trajectopy/core/settings.py
trajectopy/core/trajectory.py
trajectopy/gui/__init__.py
trajectopy/gui/app.py
trajectopy/gui/utils.py
trajectopy/gui/managers/__init__.py
trajectopy/gui/managers/file_manager.py
trajectopy/gui/managers/plot_manager.py
trajectopy/gui/managers/requests.py
trajectopy/gui/managers/session_manager.py
trajectopy/gui/managers/trajectory_manager.py
trajectopy/gui/managers/ui_manager.py
trajectopy/gui/models/__init__.py
trajectopy/gui/models/entries.py
trajectopy/gui/models/property_model.py
trajectopy/gui/models/result_model.py
trajectopy/gui/models/selection.py
trajectopy/gui/models/table_model.py
trajectopy/gui/models/trajectory_model.py
trajectopy/gui/resources/full-icon-poppins.png
trajectopy/gui/resources/icon-bg.ico
trajectopy/gui/resources/icon-bg.png
trajectopy/gui/resources/icon.png
trajectopy/gui/views/__init__.py
trajectopy/gui/views/about_window.py
trajectopy/gui/views/alignment_edit_window.py
trajectopy/gui/views/dof_organizer.py
trajectopy/gui/views/json_settings_view.py
trajectopy/gui/views/main_window.py
trajectopy/gui/views/mpl_plot_tabs.py
trajectopy/gui/views/progress_window.py
trajectopy/gui/views/properties_window.py
trajectopy/gui/views/result_context_menu.py
trajectopy/gui/views/result_selection_window.py
trajectopy/gui/views/result_table_view.py
trajectopy/gui/views/trajectory_context_menu.py
trajectopy/gui/views/trajectory_table_view.py
trajectopy/processing/__init__.py
trajectopy/processing/alignment.py
trajectopy/processing/approximation.py
trajectopy/processing/evaluation.py
trajectopy/processing/interpolation.py
trajectopy/processing/matching.py
trajectopy/processing/merging.py
trajectopy/processing/sorting.py
trajectopy/processing/lib/__init__.py
trajectopy-4.0.4.dist-info/METADATA
trajectopy-4.0.4.dist-info/WHEEL
trajectopy-4.0.4.dist-info/entry_points.txt
trajectopy-4.0.4.dist-info/licenses/LICENSE
trajectopy-4.0.4.dist-info/RECORD
