Metadata-Version: 2.4
Name: trajectopy
Version: 4.0.4
Summary: Trajectory Evaluation in Python
Project-URL: Homepage, https://gereon-t.github.io/trajectopy/
Project-URL: Documentation, https://gereon-t.github.io/trajectopy/
Project-URL: Repository, https://github.com/gereon-t/trajectopy
Project-URL: Bug Tracker, https://github.com/gereon-t/trajectopy/issues
Author-email: Gereon Tombrink <tombrink@igg.uni-bonn.de>
Maintainer-email: Gereon Tombrink <tombrink@igg.uni-bonn.de>
License: GPLv3
License-File: LICENSE
Keywords: alignment,epsg,evaluation,leverarm,robotics,similarity,trajectory
Classifier: License :: OSI Approved :: GNU General Public License v3 (GPLv3)
Classifier: Programming Language :: Python
Classifier: Programming Language :: Python :: 3
Classifier: Programming Language :: Python :: 3.10
Classifier: Programming Language :: Python :: 3.11
Classifier: Programming Language :: Python :: 3.12
Classifier: Programming Language :: Python :: 3.13
Classifier: Programming Language :: Python :: Implementation :: CPython
Classifier: Topic :: Scientific/Engineering
Requires-Python: >=3.10
Requires-Dist: autograd>=1.8.0
Requires-Dist: jinja2>=3.1.6
Requires-Dist: matplotlib>=3.9.4
Requires-Dist: networkx>=3.2.1
Requires-Dist: numpy>=2.0.2
Requires-Dist: pandas>=2.2.3
Requires-Dist: plotly>=6.1.0
Requires-Dist: pyproj>=3.6.1
Requires-Dist: rich>=14.0.0
Requires-Dist: rosbags>=0.9.23
Requires-Dist: scipy>=1.13.1
Provides-Extra: gui
Requires-Dist: pyqt6; extra == 'gui'
